MMA_MISP/__init__.py
MMA_MISP/function.py
MMA_MISP-1.2.1.dist-info/LICENSE.txt
MMA_MISP-1.2.1.dist-info/METADATA
MMA_MISP-1.2.1.dist-info/WHEEL
MMA_MISP-1.2.1.dist-info/top_level.txt
MMA_MISP-1.2.1.dist-info/RECORD
