Metadata-Version: 2.1
Name: MMA-MISP
Version: 1.2.1
Summary: A test package
Home-page: https://github.com/pypa/sampleproject
Author: ZHIHE ZHAO
Author-email: zhaozhihe98@163.com
Classifier: Programming Language :: Python :: 3.7
Classifier: License :: OSI Approved :: MIT License
Classifier: Operating System :: OS Independent
License-File: LICENSE.txt
